pasimple/__init__.py
pasimple/exceptions.py
pasimple/pa_simple.py
pasimple-0.0.2.dist-info/LICENSE
pasimple-0.0.2.dist-info/METADATA
pasimple-0.0.2.dist-info/WHEEL
pasimple-0.0.2.dist-info/top_level.txt
pasimple-0.0.2.dist-info/RECORD
