Metadata-Version: 2.1
Name: pasimple
Version: 0.0.2
Summary: Play/record audio via PulseAudio/PipeWire. A PulseAudio "simple API" wrapper.
Home-page: https://github.com/henrikschnor/pasimple
Author: Henrik Schnor
Author-email: hschnor@mailbox.org
License: MIT
Keywords: pulseaudio,pulse,pipewire,audio,recording,playback,play
Platform: posix
Classifier: Programming Language :: Python :: 3
License-File: LICENSE
